Corephone/__init__.py
Corephone/algo_name_gist.py
Corephone/algo_name_gist_uni_bn.py
Corephone/algo_uni_bn_to_en_phonetic.py
Corephone/non_unicode_to_unicode.py
Corephone/titles_and_salutations.txt
Corephone/tool_optimize_titles_and_salutations.py
Corephone/uni_bn_titles_and_salutations.txt
Corephone/vars_uni_bn_to_en_phonetic.py
Corephone-0.2.dist-info/DESCRIPTION.rst
Corephone-0.2.dist-info/METADATA
Corephone-0.2.dist-info/RECORD
Corephone-0.2.dist-info/WHEEL
Corephone-0.2.dist-info/metadata.json
Corephone-0.2.dist-info/top_level.txt
