Metadata-Version: 2.0
Name: Corephone
Version: 0.2
Summary: Useful tools to work with phonetic algorithm in Python
Home-page: https://github.com/SJamii/Phonetic-Algorithm
Author: Shafayat Jamil
Author-email: shafayatiuc@gmail.com
License: MIT
Platform: UNKNOWN
Classifier: License :: OSI Approved :: MIT License
Classifier: Programming Language :: Python :: 3
Classifier: Programming Language :: Python :: 3.6
